LICENSE.md
MANIFEST.in
README.md
setup.py
admin_argon/__init__.py
admin_argon/admin.py
admin_argon/apps.py
admin_argon/forms.py
admin_argon/models.py
admin_argon/tests.py
admin_argon/urls.py
admin_argon/utils.py
admin_argon/views.py
admin_argon/static/.gitkeep
admin_argon/static/assets/css/argon-dashboard.css
admin_argon/static/assets/css/argon-dashboard.css.map
admin_argon/static/assets/css/argon-dashboard.min.css
admin_argon/static/assets/css/forms.css
admin_argon/static/assets/css/nucleo-icons.css
admin_argon/static/assets/css/nucleo-svg.css
admin_argon/static/assets/css/widgets.css
admin_argon/static/assets/fonts/nucleo-icons.eot
admin_argon/static/assets/fonts/nucleo-icons.svg
admin_argon/static/assets/fonts/nucleo-icons.ttf
admin_argon/static/assets/fonts/nucleo-icons.woff
admin_argon/static/assets/fonts/nucleo-icons.woff2
admin_argon/static/assets/fonts/nucleo.eot
admin_argon/static/assets/fonts/nucleo.ttf
admin_argon/static/assets/fonts/nucleo.woff
admin_argon/static/assets/fonts/nucleo.woff2
admin_argon/static/assets/img/apple-icon.png
admin_argon/static/assets/img/bg-profile.jpg
admin_argon/static/assets/img/bg1.jpg
admin_argon/static/assets/img/bruce-mars.jpg
admin_argon/static/assets/img/carousel-1.jpg
admin_argon/static/assets/img/carousel-2.jpg
admin_argon/static/assets/img/carousel-3.jpg
admin_argon/static/assets/img/down-arrow-dark.svg
admin_argon/static/assets/img/down-arrow-white.svg
admin_argon/static/assets/img/down-arrow.svg
admin_argon/static/assets/img/favicon.png
admin_argon/static/assets/img/home-decor-1.jpg
admin_argon/static/assets/img/home-decor-2.jpg
admin_argon/static/assets/img/home-decor-3.jpg
admin_argon/static/assets/img/icon-calendar.svg
admin_argon/static/assets/img/icon-clock.svg
admin_argon/static/assets/img/icon-unknown-alt.svg
admin_argon/static/assets/img/icon-unknown.svg
admin_argon/static/assets/img/ivana-square.jpg
admin_argon/static/assets/img/ivancik.jpg
admin_argon/static/assets/img/kal-visuals-square.jpg
django_admin_argon_dashboard.egg-info/PKG-INFO
django_admin_argon_dashboard.egg-info/SOURCES.txt
django_admin_argon_dashboard.egg-info/dependency_links.txt
django_admin_argon_dashboard.egg-info/not-zip-safe
django_admin_argon_dashboard.egg-info/top_level.txt
